setup.cfg
setup.py
wafoo/__init__.py
wafoo.egg-info/PKG-INFO
wafoo.egg-info/SOURCES.txt
wafoo.egg-info/dependency_links.txt
wafoo.egg-info/entry_points.txt
wafoo.egg-info/not-zip-safe
wafoo.egg-info/top_level.txt