Metadata-Version: 1.0
Name: wafoo
Version: 0.0dev
Summary: web application framework of object
Home-page: UNKNOWN
Author: Atsushi Odagiri
Author-email: aodagx@gmail.com
License: MIT
Keywords: wsgi web
Platform: UNKNOWN
Classifier: Development Status :: 1 - Planning
Classifier: Environment :: Web Environment
Classifier: Topic :: Internet :: WWW/HTTP :: WSGI
Classifier: Topic :: Software Development :: Libraries :: Application Frameworks
